pyNetatmoHue.py
pyNetatmoHue-0.1.3.dist-info/LICENSE
pyNetatmoHue-0.1.3.dist-info/METADATA
pyNetatmoHue-0.1.3.dist-info/WHEEL
pyNetatmoHue-0.1.3.dist-info/top_level.txt
pyNetatmoHue-0.1.3.dist-info/RECORD
